gues/decomposable_score.py
gues/gauss_obs_l0_pen.py
gues/grues.py
gues/gues.py
gues/independence_testing.py
gues/sample.py
gues-0.3.0.data/scripts/reproduce_astat
gues-0.3.0.dist-info/LICENSE.md
gues-0.3.0.dist-info/METADATA
gues-0.3.0.dist-info/WHEEL
gues-0.3.0.dist-info/top_level.txt
gues-0.3.0.dist-info/RECORD
